{
  "version": "cp15-pricing-v1",
  "currency": "USD",
  "member": {
    "name": "HIIT56 Membership",
    "monthly": {
      "amount": 14.99,
      "interval": "month",
      "stripe_price_id": "price_1SydGhLuJBXNyJuKSEXZYxYr"
    },
    "annual": {
      "amount": 149.99,
      "interval": "year",
      "stripe_price_id": "price_1SydJ5LuJBXNyJuKDybmOTYv"
    },
    "trial_days": 7,
    "notes": "Display-only pricing. Source of truth is Stripe."
  },
  "business": {
    "name": "HIIT56 Business",
    "billing_unit": "per_location",
    "trial_days": 14,
    "tiers": {
      "starter": {
        "monthly": {
          "amount": 99.0,
          "interval": "month",
          "stripe_price_id": null
        },
        "annual": {
          "amount": 990.0,
          "interval": "year",
          "stripe_price_id": null
        },
        "notes": "Starter Stripe price IDs pending."
      },
      "pro": {
        "monthly": {
          "amount": 149.0,
          "interval": "month",
          "stripe_price_id": "price_1SydHkLuJBXNyJuKs9GnEYSd"
        },
        "annual": {
          "amount": 1490.0,
          "interval": "year",
          "stripe_price_id": "price_1SyhXPLuJBXNyJuK9vdqeAaw"
        },
        "notes": "Pro Stripe price IDs set (test)."
      }
    },
    "notes": "Per-location subscription quantity is selected at checkout (locations)."
  }
}